sqlalchemy_connector/__init__.py
sqlalchemy_connector/sqlalchemy_multiconnector.py
sqlalchemy_multiconnector/__init__.py
sqlalchemy_multiconnector/sqlalchemy_multiconnector.py
sqlalchemy_multiconnector-1.0.0.data/data/LICENSE.txt
sqlalchemy_multiconnector-1.0.0.data/data/README.md
sqlalchemy_multiconnector-1.0.0.dist-info/LICENSE.txt
sqlalchemy_multiconnector-1.0.0.dist-info/METADATA
sqlalchemy_multiconnector-1.0.0.dist-info/WHEEL
sqlalchemy_multiconnector-1.0.0.dist-info/top_level.txt
sqlalchemy_multiconnector-1.0.0.dist-info/RECORD
